[
    {
        "code": "NURA 1311",
        "sect": 1,
        "title": "THEORY, ETHICS AND PROFESSIONALISM IN NURSING",
        "chr": 3.0,
        "venue": null,
        "lect": [
            "KHIN THANDAR AUNG"
        ],
        "dayTime": [
            {
                "day": 3,
                "startTime": "14:00",
                "endTime": "17:00"
            }
        ]
    },
    {
        "code": "NURA 1311",
        "sect": 2,
        "title": "THEORY, ETHICS AND PROFESSIONALISM IN NURSING",
        "chr": 3.0,
        "venue": null,
        "lect": [
            "DR. ABDUL ALIF BIN ABDUL HAMID"
        ],
        "dayTime": [
            {
                "day": 3,
                "startTime": "09:00",
                "endTime": "10:30"
            }
        ]
    },
    {
        "code": "NURA 1311",
        "sect": 3,
        "title": "THEORY, ETHICS AND PROFESSIONALISM IN NURSING",
        "chr": 3.0,
        "venue": null,
        "lect": [
            "DR. RUSILA BINTI RUSLAN"
        ],
        "dayTime": [
            {
                "day": 2,
                "startTime": "09:00",
                "endTime": "10:30"
            }
        ]
    },
    {
        "code": "NURA 1412",
        "sect": 1,
        "title": "MEDICAL SOCIOLOGY, PSYCHOLOGY AND TRANSCULTURAL NURSING",
        "chr": 4.0,
        "venue": null,
        "lect": [
            "CHO CHO ZAW"
        ],
        "dayTime": [
            {
                "day": 1,
                "startTime": "11:00",
                "endTime": "13:00"
            }
        ]
    },
    {
        "code": "NURA 1412",
        "sect": 2,
        "title": "MEDICAL SOCIOLOGY, PSYCHOLOGY AND TRANSCULTURAL NURSING",
        "chr": 4.0,
        "venue": null,
        "lect": [
            "DR. AIRUL AZIZAN BIN ZAINUDIN"
        ],
        "dayTime": [
            {
                "day": 2,
                "startTime": "08:00",
                "endTime": "10:00"
            }
        ]
    },
    {
        "code": "NURA 1412",
        "sect": 3,
        "title": "MEDICAL SOCIOLOGY, PSYCHOLOGY AND TRANSCULTURAL NURSING",
        "chr": 4.0,
        "venue": null,
        "lect": [
            "ROHAIDA BINTI ABD WAHAB"
        ],
        "dayTime": [
            {
                "day": 3,
                "startTime": "08:00",
                "endTime": "10:00"
            }
        ]
    },
    {
        "code": "NURA 3327",
        "sect": 1,
        "title": "BIOSTATISTICS AND EPIDEMIOLOGY",
        "chr": 3.0,
        "venue": null,
        "lect": [
            "DR. WAN HASLIZA BINTI WAN MAMAT"
        ],
        "dayTime": [
            {
                "day": 2,
                "startTime": "09:45",
                "endTime": "13:00"
            }
        ]
    },
    {
        "code": "NURA 3327",
        "sect": 2,
        "title": "BIOSTATISTICS AND EPIDEMIOLOGY",
        "chr": 3.0,
        "venue": null,
        "lect": [
            "DR. WAN HASLIZA BINTI WAN MAMAT"
        ],
        "dayTime": [
            {
                "day": 2,
                "startTime": "14:00",
                "endTime": "17:00"
            }
        ]
    },
    {
        "code": "NURA 3327",
        "sect": 3,
        "title": "BIOSTATISTICS AND EPIDEMIOLOGY",
        "chr": 3.0,
        "venue": null,
        "lect": [
            "DR. MUZAITUL AKMA BINTI MUSTAPA KAMAL BASHA"
        ],
        "dayTime": [
            {
                "day": 3,
                "startTime": "14:00",
                "endTime": "17:00"
            }
        ]
    },
    {
        "code": "NURA 3327",
        "sect": 4,
        "title": "BIOSTATISTICS AND EPIDEMIOLOGY",
        "chr": 3.0,
        "venue": null,
        "lect": [
            "DR. MUZAITUL AKMA BINTI MUSTAPA KAMAL BASHA"
        ],
        "dayTime": [
            {
                "day": 1,
                "startTime": "11:30",
                "endTime": "13:00"
            }
        ]
    },
    {
        "code": "NURA 4213",
        "sect": 1,
        "title": "MANAGEMENT AND ADMINISTRATION IN NURSING PRACTICE",
        "chr": 2.0,
        "venue": null,
        "lect": [
            "DR. NORFADZILAH BINTI AHMAD"
        ],
        "dayTime": [
            {
                "day": 2,
                "startTime": "20:00",
                "endTime": "05:00"
            }
        ]
    },
    {
        "code": "NURA 4213",
        "sect": 2,
        "title": "MANAGEMENT AND ADMINISTRATION IN NURSING PRACTICE",
        "chr": 2.0,
        "venue": null,
        "lect": [
            "ROHAIDA BINTI ABD WAHAB"
        ],
        "dayTime": [
            {
                "day": 2,
                "startTime": "20:00",
                "endTime": "05:00"
            }
        ]
    },
    {
        "code": "NURA 4213",
        "sect": 3,
        "title": "MANAGEMENT AND ADMINISTRATION IN NURSING PRACTICE",
        "chr": 2.0,
        "venue": null,
        "lect": [
            "DR. NORLINDA BINTI ABD. RASHID"
        ],
        "dayTime": [
            {
                "day": 2,
                "startTime": "20:00",
                "endTime": "05:00"
            }
        ]
    },
    {
        "code": "NURA 4213",
        "sect": 4,
        "title": "MANAGEMENT AND ADMINISTRATION IN NURSING PRACTICE",
        "chr": 2.0,
        "venue": null,
        "lect": [
            "DR. MOHAMAD FIRDAUS BIN MOHAMAD ISMAIL"
        ],
        "dayTime": [
            {
                "day": 2,
                "startTime": "20:00",
                "endTime": "05:00"
            }
        ]
    },
    {
        "code": "NURA 4213",
        "sect": 5,
        "title": "MANAGEMENT AND ADMINISTRATION IN NURSING PRACTICE",
        "chr": 2.0,
        "venue": null,
        "lect": [
            "DR. SITI HAZARIAH BINTI ABDUL HAMID"
        ],
        "dayTime": [
            {
                "day": 2,
                "startTime": "20:00",
                "endTime": "05:00"
            }
        ]
    },
    {
        "code": "NURA 4213",
        "sect": 6,
        "title": "MANAGEMENT AND ADMINISTRATION IN NURSING PRACTICE",
        "chr": 2.0,
        "venue": null,
        "lect": [
            "ASSOC. PROF. DR. SALIZAR BT. MOHAMED LUDIN"
        ],
        "dayTime": [
            {
                "day": 2,
                "startTime": "20:00",
                "endTime": "05:00"
            }
        ]
    },
    {
        "code": "NURA 4213",
        "sect": 7,
        "title": "MANAGEMENT AND ADMINISTRATION IN NURSING PRACTICE",
        "chr": 2.0,
        "venue": null,
        "lect": [
            "DR. AMIRAH FATIN BINTI IBRAHIM"
        ],
        "dayTime": [
            {
                "day": 2,
                "startTime": "20:00",
                "endTime": "05:00"
            }
        ]
    },
    {
        "code": "NURA 4213",
        "sect": 8,
        "title": "MANAGEMENT AND ADMINISTRATION IN NURSING PRACTICE",
        "chr": 2.0,
        "venue": null,
        "lect": [
            "DR. SITI AZUNA BINTI ABU BAKAR"
        ],
        "dayTime": [
            {
                "day": 2,
                "startTime": "20:00",
                "endTime": "05:00"
            }
        ]
    },
    {
        "code": "NURA 4213",
        "sect": 9,
        "title": "MANAGEMENT AND ADMINISTRATION IN NURSING PRACTICE",
        "chr": 2.0,
        "venue": null,
        "lect": [
            "DR. NURUL'AIN BINTI AHAYALIMUDIN"
        ],
        "dayTime": [
            {
                "day": 2,
                "startTime": "20:00",
                "endTime": "05:00"
            }
        ]
    },
    {
        "code": "NURA 4311",
        "sect": 1,
        "title": "ISSUES, CHALLENGES AND FUTURE TRENDS IN NURSING",
        "chr": 3.0,
        "venue": null,
        "lect": [
            "DR. MOHAMAD FIRDAUS BIN MOHAMAD ISMAIL"
        ],
        "dayTime": [
            {
                "day": 1,
                "startTime": "21:00",
                "endTime": "05:00"
            }
        ]
    },
    {
        "code": "NURA 4311",
        "sect": 2,
        "title": "ISSUES, CHALLENGES AND FUTURE TRENDS IN NURSING",
        "chr": 3.0,
        "venue": null,
        "lect": [
            "DR. ASHIKIN BINTI ATAN"
        ],
        "dayTime": [
            {
                "day": 4,
                "startTime": "14:00",
                "endTime": "17:00"
            }
        ]
    },
    {
        "code": "NURA 4312",
        "sect": 1,
        "title": "MANAGEMENT AND ADMINISTRATION IN NURSING",
        "chr": 3.0,
        "venue": null,
        "lect": [
            "DR. NORFADZILAH BINTI AHMAD"
        ],
        "dayTime": [
            {
                "day": 4,
                "startTime": "09:00",
                "endTime": "12:30"
            }
        ]
    },
    {
        "code": "NURA 4312",
        "sect": 2,
        "title": "MANAGEMENT AND ADMINISTRATION IN NURSING",
        "chr": 3.0,
        "venue": null,
        "lect": [
            "ASSOC. PROF. DR. SALIZAR BT. MOHAMED LUDIN"
        ],
        "dayTime": [
            {
                "day": 2,
                "startTime": "21:00",
                "endTime": "05:00"
            }
        ]
    },
    {
        "code": "NURB 1213",
        "sect": 1,
        "title": "ANATOMY AND PHYSIOLOGY 1",
        "chr": 2.0,
        "venue": null,
        "lect": [
            "DR. NORLINDA BINTI ABD. RASHID"
        ],
        "dayTime": [
            {
                "day": 1,
                "startTime": "15:00",
                "endTime": "17:00"
            }
        ]
    },
    {
        "code": "NURB 1213",
        "sect": 2,
        "title": "ANATOMY AND PHYSIOLOGY 1",
        "chr": 2.0,
        "venue": null,
        "lect": [
            "DR. AZMIR BIN AHMAD"
        ],
        "dayTime": [
            {
                "day": 1,
                "startTime": "11:00",
                "endTime": "13:00"
            }
        ]
    },
    {
        "code": "NURB 1213",
        "sect": 3,
        "title": "ANATOMY AND PHYSIOLOGY 1",
        "chr": 2.0,
        "venue": null,
        "lect": [
            "DR. REDZUAN NUL HAKIM BIN ABDUL RAZAK"
        ],
        "dayTime": [
            {
                "day": 3,
                "startTime": "14:00",
                "endTime": "16:00"
            }
        ]
    },
    {
        "code": "NURB 1214",
        "sect": 1,
        "title": "BIOCHEMISTRY FOR NURSING",
        "chr": 2.0,
        "venue": null,
        "lect": [
            "DR. SHIDQIYYAH BINTI ABD HAMID"
        ],
        "dayTime": [
            {
                "day": 3,
                "startTime": "08:00",
                "endTime": "10:00"
            }
        ]
    },
    {
        "code": "NURB 1214",
        "sect": 2,
        "title": "BIOCHEMISTRY FOR NURSING",
        "chr": 2.0,
        "venue": null,
        "lect": [
            "DR. NURHAZIRAH BINTI ZAINUL AZLAN"
        ],
        "dayTime": [
            {
                "day": 2,
                "startTime": "15:00",
                "endTime": "17:00"
            }
        ]
    },
    {
        "code": "NURB 1214",
        "sect": 3,
        "title": "BIOCHEMISTRY FOR NURSING",
        "chr": 2.0,
        "venue": null,
        "lect": [
            "DR. SYAMSUL BIN AHMAD ARIFIN"
        ],
        "dayTime": [
            {
                "day": 2,
                "startTime": "08:00",
                "endTime": "10:00"
            }
        ]
    },
    {
        "code": "NURB 1315",
        "sect": 1,
        "title": "MICROBIOLOGY, IMMUNOLOGY AND PARASITOLOGY",
        "chr": 3.0,
        "venue": null,
        "lect": [
            "DR. MOHD HANIF BIN JAINLABDIN"
        ],
        "dayTime": [
            {
                "day": 2,
                "startTime": "09:45",
                "endTime": "13:00"
            }
        ]
    },
    {
        "code": "NURB 1315",
        "sect": 2,
        "title": "MICROBIOLOGY, IMMUNOLOGY AND PARASITOLOGY",
        "chr": 3.0,
        "venue": null,
        "lect": [
            "DR. NURHAZIRAH BINTI ZAINUL AZLAN"
        ],
        "dayTime": [
            {
                "day": 3,
                "startTime": "14:00",
                "endTime": "17:00"
            }
        ]
    },
    {
        "code": "NURB 1315",
        "sect": 3,
        "title": "MICROBIOLOGY, IMMUNOLOGY AND PARASITOLOGY",
        "chr": 3.0,
        "venue": null,
        "lect": [
            "DR. NORATIKAH BT. OTHMAN"
        ],
        "dayTime": [
            {
                "day": 1,
                "startTime": "11:30",
                "endTime": "13:00"
            }
        ]
    },
    {
        "code": "NURB 2215",
        "sect": 1,
        "title": "SYSTEMIC PHARMACOLOGY",
        "chr": 2.0,
        "venue": null,
        "lect": [
            "DR. SYAMSUL BIN AHMAD ARIFIN"
        ],
        "dayTime": [
            {
                "day": 2,
                "startTime": "14:00",
                "endTime": "16:00"
            }
        ]
    },
    {
        "code": "NURB 2215",
        "sect": 2,
        "title": "SYSTEMIC PHARMACOLOGY",
        "chr": 2.0,
        "venue": null,
        "lect": [
            "DR. MOHD. AZRI BIN ABD. JALIL"
        ],
        "dayTime": [
            {
                "day": 1,
                "startTime": "11:00",
                "endTime": "13:00"
            }
        ]
    },
    {
        "code": "NURB 2215",
        "sect": 3,
        "title": "SYSTEMIC PHARMACOLOGY",
        "chr": 2.0,
        "venue": null,
        "lect": [
            "DR. SHIDQIYYAH BINTI ABD HAMID"
        ],
        "dayTime": [
            {
                "day": 4,
                "startTime": "11:00",
                "endTime": "13:00"
            }
        ]
    },
    {
        "code": "NURC 2411",
        "sect": 1,
        "title": "FUNDAMENTAL OF MEDICAL-SURGICAL AND SPECIAL SENSES NURSING",
        "chr": 4.0,
        "venue": null,
        "lect": [
            "DR. SITI NUR ILLIANI BINTI JAAFAR"
        ],
        "dayTime": [
            {
                "day": 1,
                "startTime": "08:00",
                "endTime": "10:00"
            }
        ]
    },
    {
        "code": "NURC 2411",
        "sect": 2,
        "title": "FUNDAMENTAL OF MEDICAL-SURGICAL AND SPECIAL SENSES NURSING",
        "chr": 4.0,
        "venue": null,
        "lect": [
            "ASSOC. PROF. DR. AZLINA BT. DAUD"
        ],
        "dayTime": [
            {
                "day": 2,
                "startTime": "08:00",
                "endTime": "10:00"
            }
        ]
    },
    {
        "code": "NURC 2411",
        "sect": 3,
        "title": "FUNDAMENTAL OF MEDICAL-SURGICAL AND SPECIAL SENSES NURSING",
        "chr": 4.0,
        "venue": null,
        "lect": [
            "DR. AYUNI ASMA' BINTI BAHARUDIN"
        ],
        "dayTime": [
            {
                "day": 1,
                "startTime": "11:00",
                "endTime": "13:00"
            }
        ]
    },
    {
        "code": "NURC 2412",
        "sect": 1,
        "title": "HEMOPOIETIC,MUSCULOSKELETAL AND GENITOURINARY NURSING",
        "chr": 4.0,
        "venue": null,
        "lect": [
            "THANDAR SOE @ SUMAIYAH JAMALUDIN"
        ],
        "dayTime": [
            {
                "day": 2,
                "startTime": "11:00",
                "endTime": "13:00"
            }
        ]
    },
    {
        "code": "NURC 2412",
        "sect": 2,
        "title": "HEMOPOIETIC,MUSCULOSKELETAL AND GENITOURINARY NURSING",
        "chr": 4.0,
        "venue": null,
        "lect": [
            "MASMUNAA BINTI HASSAN"
        ],
        "dayTime": [
            {
                "day": 2,
                "startTime": "11:00",
                "endTime": "13:00"
            }
        ]
    },
    {
        "code": "NURC 2412",
        "sect": 3,
        "title": "HEMOPOIETIC,MUSCULOSKELETAL AND GENITOURINARY NURSING",
        "chr": 4.0,
        "venue": null,
        "lect": [
            "DR. NIK NOOR KAUSSAR BINTI NIK MOHD HATTA"
        ],
        "dayTime": [
            {
                "day": 4,
                "startTime": "11:00",
                "endTime": "13:00"
            }
        ]
    },
    {
        "code": "NURC 2413",
        "sect": 1,
        "title": "CARDIOVASCULAR,RESPIRATORY AND ENDOCRINE NURSING",
        "chr": 4.0,
        "venue": null,
        "lect": [
            "DR. HANIDA HANI BINTI MOHD MOKHTAR"
        ],
        "dayTime": [
            {
                "day": 4,
                "startTime": "14:00",
                "endTime": "16:00"
            }
        ]
    },
    {
        "code": "NURC 2413",
        "sect": 2,
        "title": "CARDIOVASCULAR,RESPIRATORY AND ENDOCRINE NURSING",
        "chr": 4.0,
        "venue": null,
        "lect": [
            "ASSOC. PROF. DR. SANISAH BINTI SAIDI"
        ],
        "dayTime": [
            {
                "day": 4,
                "startTime": "14:00",
                "endTime": "16:00"
            }
        ]
    },
    {
        "code": "NURC 2413",
        "sect": 3,
        "title": "CARDIOVASCULAR,RESPIRATORY AND ENDOCRINE NURSING",
        "chr": 4.0,
        "venue": null,
        "lect": [
            "THANDAR SOE @ SUMAIYAH JAMALUDIN"
        ],
        "dayTime": [
            {
                "day": 1,
                "startTime": "14:00",
                "endTime": "16:00"
            }
        ]
    },
    {
        "code": "NURC 2414",
        "sect": 1,
        "title": "GASTROINTESTINAL,HEPATOBILIARY AND NEUROLOGICAL NURSING",
        "chr": 4.0,
        "venue": null,
        "lect": [
            "DR. SITI ZUHAIDAH BINTI SHAHADAN"
        ],
        "dayTime": [
            {
                "day": 1,
                "startTime": "11:00",
                "endTime": "13:00"
            }
        ]
    },
    {
        "code": "NURC 2414",
        "sect": 2,
        "title": "GASTROINTESTINAL,HEPATOBILIARY AND NEUROLOGICAL NURSING",
        "chr": 4.0,
        "venue": null,
        "lect": [
            "MASMUNAA BINTI HASSAN"
        ],
        "dayTime": [
            {
                "day": 2,
                "startTime": "08:00",
                "endTime": "10:00"
            }
        ]
    },
    {
        "code": "NURC 2414",
        "sect": 3,
        "title": "GASTROINTESTINAL,HEPATOBILIARY AND NEUROLOGICAL NURSING",
        "chr": 4.0,
        "venue": null,
        "lect": [
            "DR. AYUNI ASMA' BINTI BAHARUDIN"
        ],
        "dayTime": [
            {
                "day": 1,
                "startTime": "08:00",
                "endTime": "10:00"
            }
        ]
    },
    {
        "code": "NURD 3325",
        "sect": 1,
        "title": "EMERGENCY, THEATRE AND INTENSIVE CARE NURSING PRACTICE",
        "chr": 3.0,
        "venue": null,
        "lect": [
            "ROHAIDA BINTI ABD WAHAB"
        ],
        "dayTime": []
    },
    {
        "code": "NURD 3415",
        "sect": 1,
        "title": "EMERGENCY, THEATRE AND INTENSIVE CARE NURSING",
        "chr": 4.0,
        "venue": null,
        "lect": [
            "DR. SITI AZUNA BINTI ABU BAKAR"
        ],
        "dayTime": [
            {
                "day": 3,
                "startTime": "08:00",
                "endTime": "10:00"
            }
        ]
    },
    {
        "code": "NURD 3415",
        "sect": 2,
        "title": "EMERGENCY, THEATRE AND INTENSIVE CARE NURSING",
        "chr": 4.0,
        "venue": null,
        "lect": [
            "ASSOC. PROF. DR. MOHD. SAID BIN NURUMAL"
        ],
        "dayTime": [
            {
                "day": 2,
                "startTime": "08:00",
                "endTime": "10:00"
            }
        ]
    },
    {
        "code": "NURD 3415",
        "sect": 3,
        "title": "EMERGENCY, THEATRE AND INTENSIVE CARE NURSING",
        "chr": 4.0,
        "venue": null,
        "lect": [
            "DR. ABDUL ALIF BIN ABDUL HAMID"
        ],
        "dayTime": [
            {
                "day": 1,
                "startTime": "11:00",
                "endTime": "13:00"
            }
        ]
    },
    {
        "code": "NURD 3415",
        "sect": 4,
        "title": "EMERGENCY, THEATRE AND INTENSIVE CARE NURSING",
        "chr": 4.0,
        "venue": null,
        "lect": [
            "DR. RUSILA BINTI RUSLAN"
        ],
        "dayTime": [
            {
                "day": 2,
                "startTime": "11:00",
                "endTime": "13:00"
            }
        ]
    },
    {
        "code": "NURE 3212",
        "sect": 1,
        "title": "CHILD HEALTH NURSING",
        "chr": 2.0,
        "venue": null,
        "lect": [
            "DR. LEE SIEW PIEN"
        ],
        "dayTime": [
            {
                "day": 5,
                "startTime": "10:30",
                "endTime": "12:30"
            }
        ]
    },
    {
        "code": "NURE 3212",
        "sect": 2,
        "title": "CHILD HEALTH NURSING",
        "chr": 2.0,
        "venue": null,
        "lect": [
            "DR. LEE SIEW PIEN"
        ],
        "dayTime": [
            {
                "day": 1,
                "startTime": "11:00",
                "endTime": "13:00"
            }
        ]
    },
    {
        "code": "NURE 3212",
        "sect": 3,
        "title": "CHILD HEALTH NURSING",
        "chr": 2.0,
        "venue": null,
        "lect": [
            "DR. SITI HAZARIAH BINTI ABDUL HAMID"
        ],
        "dayTime": [
            {
                "day": 2,
                "startTime": "08:00",
                "endTime": "10:00"
            }
        ]
    },
    {
        "code": "NURE 3212",
        "sect": 4,
        "title": "CHILD HEALTH NURSING",
        "chr": 2.0,
        "venue": null,
        "lect": [
            "DR. AMIRAH FATIN BINTI IBRAHIM"
        ],
        "dayTime": [
            {
                "day": 3,
                "startTime": "08:00",
                "endTime": "10:00"
            }
        ]
    },
    {
        "code": "NURE 3214",
        "sect": 1,
        "title": "MENTAL HEALTH NURSING",
        "chr": 2.0,
        "venue": null,
        "lect": [
            "RAMLAH BINTI MAMAT"
        ],
        "dayTime": [
            {
                "day": 1,
                "startTime": "08:00",
                "endTime": "10:00"
            }
        ]
    },
    {
        "code": "NURE 3214",
        "sect": 2,
        "title": "MENTAL HEALTH NURSING",
        "chr": 2.0,
        "venue": null,
        "lect": [
            "RAMLAH BINTI MAMAT"
        ],
        "dayTime": [
            {
                "day": 1,
                "startTime": "15:00",
                "endTime": "17:00"
            }
        ]
    },
    {
        "code": "NURE 3214",
        "sect": 3,
        "title": "MENTAL HEALTH NURSING",
        "chr": 2.0,
        "venue": null,
        "lect": [
            "DR. NURASIKIN BINTI MOHAMAD SHARIFF"
        ],
        "dayTime": [
            {
                "day": 2,
                "startTime": "15:00",
                "endTime": "17:00"
            }
        ]
    },
    {
        "code": "NURE 3214",
        "sect": 4,
        "title": "MENTAL HEALTH NURSING",
        "chr": 2.0,
        "venue": null,
        "lect": [
            "DR. NURASIKIN BINTI MOHAMAD SHARIFF"
        ],
        "dayTime": [
            {
                "day": 5,
                "startTime": "08:00",
                "endTime": "10:00"
            }
        ]
    },
    {
        "code": "NURE 3311",
        "sect": 1,
        "title": "MATERNAL-NEWBORN AND GYNAECOLOGICAL NURSING",
        "chr": 3.0,
        "venue": null,
        "lect": [
            "ASSOC. PROF. DR. SITI MARIAM BINTI MUDA"
        ],
        "dayTime": [
            {
                "day": 1,
                "startTime": "15:00",
                "endTime": "17:00"
            }
        ]
    },
    {
        "code": "NURE 3311",
        "sect": 2,
        "title": "MATERNAL-NEWBORN AND GYNAECOLOGICAL NURSING",
        "chr": 3.0,
        "venue": null,
        "lect": [
            "ASSOC. PROF. DR. SITI MARIAM BINTI MUDA"
        ],
        "dayTime": [
            {
                "day": 3,
                "startTime": "08:00",
                "endTime": "10:00"
            }
        ]
    },
    {
        "code": "NURE 3311",
        "sect": 3,
        "title": "MATERNAL-NEWBORN AND GYNAECOLOGICAL NURSING",
        "chr": 3.0,
        "venue": null,
        "lect": [
            "ASSOC. PROF. DR. SITI ROSHAIDAI BINTI MOHD ARIFIN"
        ],
        "dayTime": [
            {
                "day": 2,
                "startTime": "11:00",
                "endTime": "13:00"
            }
        ]
    },
    {
        "code": "NURE 3311",
        "sect": 4,
        "title": "MATERNAL-NEWBORN AND GYNAECOLOGICAL NURSING",
        "chr": 3.0,
        "venue": null,
        "lect": [
            "ASSOC. PROF. DR. SITI ROSHAIDAI BINTI MOHD ARIFIN"
        ],
        "dayTime": [
            {
                "day": 2,
                "startTime": "08:00",
                "endTime": "10:00"
            }
        ]
    },
    {
        "code": "NURE 3413",
        "sect": 1,
        "title": "COMMUNITY HEALTH NURSING",
        "chr": 4.0,
        "venue": null,
        "lect": [
            "DR. ANIAWANIS BINTI MAKHTAR"
        ],
        "dayTime": [
            {
                "day": 3,
                "startTime": "11:00",
                "endTime": "13:00"
            }
        ]
    },
    {
        "code": "NURE 3413",
        "sect": 2,
        "title": "COMMUNITY HEALTH NURSING",
        "chr": 4.0,
        "venue": null,
        "lect": [
            "DR. ANIAWANIS BINTI MAKHTAR"
        ],
        "dayTime": [
            {
                "day": 2,
                "startTime": "11:00",
                "endTime": "13:00"
            }
        ]
    },
    {
        "code": "NURE 3413",
        "sect": 3,
        "title": "COMMUNITY HEALTH NURSING",
        "chr": 4.0,
        "venue": null,
        "lect": [
            "DR. HALIZA HASAN"
        ],
        "dayTime": [
            {
                "day": 1,
                "startTime": "15:00",
                "endTime": "17:00"
            }
        ]
    },
    {
        "code": "NURE 3413",
        "sect": 4,
        "title": "COMMUNITY HEALTH NURSING",
        "chr": 4.0,
        "venue": null,
        "lect": [
            "DR. SHARIFAH MUNIRAH BINTI SYED ELIAS"
        ],
        "dayTime": [
            {
                "day": 1,
                "startTime": "09:00",
                "endTime": "11:00"
            }
        ]
    },
    {
        "code": "NURF 3327",
        "sect": 1,
        "title": "INNOVATION IN NURSING",
        "chr": 3.0,
        "venue": null,
        "lect": [
            "DR. AZMIR BIN AHMAD"
        ],
        "dayTime": []
    },
    {
        "code": "NURF 4314",
        "sect": 1,
        "title": "DISCOVERY OF SPECIALIZATION IN NURSING",
        "chr": 3.0,
        "venue": null,
        "lect": [
            "DR. MOHD KHAIRUL ZUL HASYMI BIN FIRDAUS"
        ],
        "dayTime": [
            {
                "day": 1,
                "startTime": "20:00",
                "endTime": "05:00"
            }
        ]
    },
    {
        "code": "NURF 4314",
        "sect": 2,
        "title": "DISCOVERY OF SPECIALIZATION IN NURSING",
        "chr": 3.0,
        "venue": null,
        "lect": [
            "DR. NIK NOOR KAUSSAR BINTI NIK MOHD HATTA"
        ],
        "dayTime": [
            {
                "day": 1,
                "startTime": "20:00",
                "endTime": "05:00"
            }
        ]
    },
    {
        "code": "NURF 4314",
        "sect": 3,
        "title": "DISCOVERY OF SPECIALIZATION IN NURSING",
        "chr": 3.0,
        "venue": null,
        "lect": [
            "DR. HANIDA HANI BINTI MOHD MOKHTAR"
        ],
        "dayTime": [
            {
                "day": 1,
                "startTime": "20:00",
                "endTime": "05:00"
            }
        ]
    },
    {
        "code": "NURF 4314",
        "sect": 4,
        "title": "DISCOVERY OF SPECIALIZATION IN NURSING",
        "chr": 3.0,
        "venue": null,
        "lect": [
            "DR. NURUL'AIN BINTI AHAYALIMUDIN"
        ],
        "dayTime": [
            {
                "day": 1,
                "startTime": "20:00",
                "endTime": "05:00"
            }
        ]
    },
    {
        "code": "NURF 4314",
        "sect": 5,
        "title": "DISCOVERY OF SPECIALIZATION IN NURSING",
        "chr": 3.0,
        "venue": null,
        "lect": [
            "DR. ABDUL ALIF BIN ABDUL HAMID"
        ],
        "dayTime": [
            {
                "day": 1,
                "startTime": "20:00",
                "endTime": "05:00"
            }
        ]
    },
    {
        "code": "NURF 4314",
        "sect": 6,
        "title": "DISCOVERY OF SPECIALIZATION IN NURSING",
        "chr": 3.0,
        "venue": null,
        "lect": [
            "KHIN THANDAR AUNG"
        ],
        "dayTime": [
            {
                "day": 1,
                "startTime": "20:00",
                "endTime": "05:00"
            }
        ]
    },
    {
        "code": "NURF 4314",
        "sect": 7,
        "title": "DISCOVERY OF SPECIALIZATION IN NURSING",
        "chr": 3.0,
        "venue": null,
        "lect": [
            "DR. AIRUL AZIZAN BIN ZAINUDIN"
        ],
        "dayTime": [
            {
                "day": 1,
                "startTime": "20:00",
                "endTime": "05:00"
            }
        ]
    },
    {
        "code": "NURF 4314",
        "sect": 8,
        "title": "DISCOVERY OF SPECIALIZATION IN NURSING",
        "chr": 3.0,
        "venue": null,
        "lect": [
            "ASSOC. PROF. DR. SITI MARIAM BINTI MUDA"
        ],
        "dayTime": [
            {
                "day": 1,
                "startTime": "20:00",
                "endTime": "05:00"
            }
        ]
    },
    {
        "code": "NURF 4314",
        "sect": 9,
        "title": "DISCOVERY OF SPECIALIZATION IN NURSING",
        "chr": 3.0,
        "venue": null,
        "lect": [
            "DR. HALIZA HASAN"
        ],
        "dayTime": [
            {
                "day": 1,
                "startTime": "20:00",
                "endTime": "05:00"
            }
        ]
    },
    {
        "code": "NURF 4314",
        "sect": 10,
        "title": "DISCOVERY OF SPECIALIZATION IN NURSING",
        "chr": 3.0,
        "venue": null,
        "lect": [
            "DR. SHARIFAH MUNIRAH BINTI SYED ELIAS"
        ],
        "dayTime": [
            {
                "day": 1,
                "startTime": "20:00",
                "endTime": "05:00"
            }
        ]
    },
    {
        "code": "NURF 4314",
        "sect": 11,
        "title": "DISCOVERY OF SPECIALIZATION IN NURSING",
        "chr": 3.0,
        "venue": null,
        "lect": [
            "ASSOC. PROF. DR. SITI ROSHAIDAI BINTI MOHD ARIFIN"
        ],
        "dayTime": [
            {
                "day": 1,
                "startTime": "20:00",
                "endTime": "05:00"
            }
        ]
    },
    {
        "code": "NURF 4314",
        "sect": 12,
        "title": "DISCOVERY OF SPECIALIZATION IN NURSING",
        "chr": 3.0,
        "venue": null,
        "lect": [
            "DR. SITI HAZARIAH BINTI ABDUL HAMID"
        ],
        "dayTime": [
            {
                "day": 1,
                "startTime": "20:00",
                "endTime": "05:00"
            }
        ]
    },
    {
        "code": "NURF 4415",
        "sect": 1,
        "title": "FINAL YEAR RESEARCH PROJECT I",
        "chr": 4.0,
        "venue": null,
        "lect": [
            "DR. NURHAZIRAH BINTI ZAINUL AZLAN"
        ],
        "dayTime": []
    },
    {
        "code": "NURF 4415",
        "sect": 2,
        "title": "FINAL YEAR RESEARCH PROJECT I",
        "chr": 4.0,
        "venue": null,
        "lect": [
            "CHO CHO ZAW"
        ],
        "dayTime": []
    },
    {
        "code": "NURF 4415",
        "sect": 3,
        "title": "FINAL YEAR RESEARCH PROJECT I",
        "chr": 4.0,
        "venue": null,
        "lect": [
            "DR. MOHAMAD FIRDAUS BIN MOHAMAD ISMAIL"
        ],
        "dayTime": []
    },
    {
        "code": "NURF 4415",
        "sect": 4,
        "title": "FINAL YEAR RESEARCH PROJECT I",
        "chr": 4.0,
        "venue": null,
        "lect": [
            "DR. NORFADZILAH BINTI AHMAD"
        ],
        "dayTime": []
    },
    {
        "code": "NURF 4415",
        "sect": 5,
        "title": "FINAL YEAR RESEARCH PROJECT I",
        "chr": 4.0,
        "venue": null,
        "lect": [
            "DR. SITI NOORKHAIRINA BINTI SOWTALI"
        ],
        "dayTime": []
    },
    {
        "code": "NURF 4415",
        "sect": 6,
        "title": "FINAL YEAR RESEARCH PROJECT I",
        "chr": 4.0,
        "venue": null,
        "lect": [
            "DR. WAN HASLIZA BINTI WAN MAMAT"
        ],
        "dayTime": []
    },
    {
        "code": "NURF 4415",
        "sect": 7,
        "title": "FINAL YEAR RESEARCH PROJECT I",
        "chr": 4.0,
        "venue": null,
        "lect": [
            "DR. AZMIR BIN AHMAD"
        ],
        "dayTime": []
    },
    {
        "code": "NURF 4415",
        "sect": 8,
        "title": "FINAL YEAR RESEARCH PROJECT I",
        "chr": 4.0,
        "venue": null,
        "lect": [
            "DR. MOHD. AZRI BIN ABD. JALIL"
        ],
        "dayTime": []
    },
    {
        "code": "NURF 4415",
        "sect": 9,
        "title": "FINAL YEAR RESEARCH PROJECT I",
        "chr": 4.0,
        "venue": null,
        "lect": [
            "DR. MOHD HANIF BIN JAINLABDIN"
        ],
        "dayTime": []
    },
    {
        "code": "NURF 4415",
        "sect": 10,
        "title": "FINAL YEAR RESEARCH PROJECT I",
        "chr": 4.0,
        "venue": null,
        "lect": [
            "DR. MUHAMMAD LOKMAN BIN MD. ISA"
        ],
        "dayTime": []
    },
    {
        "code": "NURF 4415",
        "sect": 11,
        "title": "FINAL YEAR RESEARCH PROJECT I",
        "chr": 4.0,
        "venue": null,
        "lect": [
            "DR. NORATIKAH BT. OTHMAN"
        ],
        "dayTime": []
    },
    {
        "code": "NURF 4415",
        "sect": 12,
        "title": "FINAL YEAR RESEARCH PROJECT I",
        "chr": 4.0,
        "venue": null,
        "lect": [
            "DR. NORLINDA BINTI ABD. RASHID"
        ],
        "dayTime": []
    },
    {
        "code": "NURF 4415",
        "sect": 13,
        "title": "FINAL YEAR RESEARCH PROJECT I",
        "chr": 4.0,
        "venue": null,
        "lect": [
            "DR. REDZUAN NUL HAKIM BIN ABDUL RAZAK"
        ],
        "dayTime": []
    },
    {
        "code": "NURF 4415",
        "sect": 14,
        "title": "FINAL YEAR RESEARCH PROJECT I",
        "chr": 4.0,
        "venue": null,
        "lect": [
            "DR. SYAMSUL BIN AHMAD ARIFIN"
        ],
        "dayTime": []
    },
    {
        "code": "NURF 4415",
        "sect": 15,
        "title": "FINAL YEAR RESEARCH PROJECT I",
        "chr": 4.0,
        "venue": null,
        "lect": [
            "DR. TENGKU MUHAMAD FARIS SYAFIQ BIN TENGKU ZAKARIA"
        ],
        "dayTime": []
    },
    {
        "code": "NURF 4415",
        "sect": 16,
        "title": "FINAL YEAR RESEARCH PROJECT I",
        "chr": 4.0,
        "venue": null,
        "lect": [
            "ASSOC. PROF. DR. AZLINA BT. DAUD"
        ],
        "dayTime": []
    },
    {
        "code": "NURF 4415",
        "sect": 17,
        "title": "FINAL YEAR RESEARCH PROJECT I",
        "chr": 4.0,
        "venue": null,
        "lect": [
            "DR. HANIDA HANI BINTI MOHD MOKHTAR"
        ],
        "dayTime": []
    },
    {
        "code": "NURF 4415",
        "sect": 18,
        "title": "FINAL YEAR RESEARCH PROJECT I",
        "chr": 4.0,
        "venue": null,
        "lect": [
            "DR. CHE AZUNIE BINTI CHE ABDULLAH"
        ],
        "dayTime": []
    },
    {
        "code": "NURF 4415",
        "sect": 19,
        "title": "FINAL YEAR RESEARCH PROJECT I",
        "chr": 4.0,
        "venue": null,
        "lect": [
            "DR. NIK NOOR KAUSSAR BINTI NIK MOHD HATTA"
        ],
        "dayTime": []
    },
    {
        "code": "NURF 4415",
        "sect": 20,
        "title": "FINAL YEAR RESEARCH PROJECT I",
        "chr": 4.0,
        "venue": null,
        "lect": [
            "DR. MUZAITUL AKMA BINTI MUSTAPA KAMAL BASHA"
        ],
        "dayTime": []
    },
    {
        "code": "NURF 4415",
        "sect": 21,
        "title": "FINAL YEAR RESEARCH PROJECT I",
        "chr": 4.0,
        "venue": null,
        "lect": [
            "ASSOC. PROF. DR. SANISAH BINTI SAIDI"
        ],
        "dayTime": []
    },
    {
        "code": "NURF 4415",
        "sect": 22,
        "title": "FINAL YEAR RESEARCH PROJECT I",
        "chr": 4.0,
        "venue": null,
        "lect": [
            "DR. SITI NUR ILLIANI BINTI JAAFAR"
        ],
        "dayTime": []
    },
    {
        "code": "NURF 4415",
        "sect": 23,
        "title": "FINAL YEAR RESEARCH PROJECT I",
        "chr": 4.0,
        "venue": null,
        "lect": [
            "DR. ASHIKIN BINTI ATAN"
        ],
        "dayTime": []
    },
    {
        "code": "NURF 4415",
        "sect": 24,
        "title": "FINAL YEAR RESEARCH PROJECT I",
        "chr": 4.0,
        "venue": null,
        "lect": [
            "KHIN THANDAR AUNG"
        ],
        "dayTime": []
    },
    {
        "code": "NURF 4415",
        "sect": 25,
        "title": "FINAL YEAR RESEARCH PROJECT I",
        "chr": 4.0,
        "venue": null,
        "lect": [
            "ASSOC. PROF. DR. MOHD. SAID BIN NURUMAL"
        ],
        "dayTime": []
    },
    {
        "code": "NURF 4415",
        "sect": 26,
        "title": "FINAL YEAR RESEARCH PROJECT I",
        "chr": 4.0,
        "venue": null,
        "lect": [
            "DR. NOOR AZIZAH BINTI MOHD ALI"
        ],
        "dayTime": []
    },
    {
        "code": "NURF 4415",
        "sect": 27,
        "title": "FINAL YEAR RESEARCH PROJECT I",
        "chr": 4.0,
        "venue": null,
        "lect": [
            "DR. NURUL'AIN BINTI AHAYALIMUDIN"
        ],
        "dayTime": []
    },
    {
        "code": "NURF 4415",
        "sect": 28,
        "title": "FINAL YEAR RESEARCH PROJECT I",
        "chr": 4.0,
        "venue": null,
        "lect": [
            "ASSOC. PROF. DR. SALIZAR BT. MOHAMED LUDIN"
        ],
        "dayTime": []
    },
    {
        "code": "NURF 4415",
        "sect": 29,
        "title": "FINAL YEAR RESEARCH PROJECT I",
        "chr": 4.0,
        "venue": null,
        "lect": [
            "THANDAR SOE @ SUMAIYAH JAMALUDIN"
        ],
        "dayTime": []
    },
    {
        "code": "NURF 4415",
        "sect": 30,
        "title": "FINAL YEAR RESEARCH PROJECT I",
        "chr": 4.0,
        "venue": null,
        "lect": [
            "DR. ANIAWANIS BINTI MAKHTAR"
        ],
        "dayTime": []
    },
    {
        "code": "NURF 4415",
        "sect": 31,
        "title": "FINAL YEAR RESEARCH PROJECT I",
        "chr": 4.0,
        "venue": null,
        "lect": [
            "DR. HALIZA HASAN"
        ],
        "dayTime": []
    },
    {
        "code": "NURF 4415",
        "sect": 32,
        "title": "FINAL YEAR RESEARCH PROJECT I",
        "chr": 4.0,
        "venue": null,
        "lect": [
            "DR. LEE SIEW PIEN"
        ],
        "dayTime": []
    },
    {
        "code": "NURF 4415",
        "sect": 33,
        "title": "FINAL YEAR RESEARCH PROJECT I",
        "chr": 4.0,
        "venue": null,
        "lect": [
            "DR. NURASIKIN BINTI MOHAMAD SHARIFF"
        ],
        "dayTime": []
    },
    {
        "code": "NURF 4415",
        "sect": 34,
        "title": "FINAL YEAR RESEARCH PROJECT I",
        "chr": 4.0,
        "venue": null,
        "lect": [
            "DR. SHARIFAH MUNIRAH BINTI SYED ELIAS"
        ],
        "dayTime": []
    },
    {
        "code": "NURF 4415",
        "sect": 35,
        "title": "FINAL YEAR RESEARCH PROJECT I",
        "chr": 4.0,
        "venue": null,
        "lect": [
            "DR. SITI HAZARIAH BINTI ABDUL HAMID"
        ],
        "dayTime": []
    },
    {
        "code": "NURF 4415",
        "sect": 36,
        "title": "FINAL YEAR RESEARCH PROJECT I",
        "chr": 4.0,
        "venue": null,
        "lect": [
            "ASSOC. PROF. DR. SITI MARIAM BINTI MUDA"
        ],
        "dayTime": []
    },
    {
        "code": "NURF 4415",
        "sect": 37,
        "title": "FINAL YEAR RESEARCH PROJECT I",
        "chr": 4.0,
        "venue": null,
        "lect": [
            "ASSOC. PROF. DR. SITI ROSHAIDAI BINTI MOHD ARIFIN"
        ],
        "dayTime": []
    },
    {
        "code": "NURF 4415",
        "sect": 38,
        "title": "FINAL YEAR RESEARCH PROJECT I",
        "chr": 4.0,
        "venue": null,
        "lect": [
            "DR. AMIRAH FATIN BINTI IBRAHIM"
        ],
        "dayTime": []
    },
    {
        "code": "NURF 4415",
        "sect": 39,
        "title": "FINAL YEAR RESEARCH PROJECT I",
        "chr": 4.0,
        "venue": null,
        "lect": [
            "DR. AIRUL AZIZAN BIN ZAINUDIN"
        ],
        "dayTime": []
    },
    {
        "code": "NURF 4415",
        "sect": 40,
        "title": "FINAL YEAR RESEARCH PROJECT I",
        "chr": 4.0,
        "venue": null,
        "lect": [
            "DR. ABDUL ALIF BIN ABDUL HAMID"
        ],
        "dayTime": []
    },
    {
        "code": "NURF 4415",
        "sect": 41,
        "title": "FINAL YEAR RESEARCH PROJECT I",
        "chr": 4.0,
        "venue": null,
        "lect": [
            "DR. SHIDQIYYAH BINTI ABD HAMID"
        ],
        "dayTime": []
    },
    {
        "code": "NURF 4415",
        "sect": 42,
        "title": "FINAL YEAR RESEARCH PROJECT I",
        "chr": 4.0,
        "venue": null,
        "lect": [
            "DR. SITI AZUNA BINTI ABU BAKAR"
        ],
        "dayTime": []
    },
    {
        "code": "NURF 4415",
        "sect": 43,
        "title": "FINAL YEAR RESEARCH PROJECT I",
        "chr": 4.0,
        "venue": null,
        "lect": [
            "DR. RUSILA BINTI RUSLAN"
        ],
        "dayTime": []
    },
    {
        "code": "NURF 4415",
        "sect": 44,
        "title": "FINAL YEAR RESEARCH PROJECT I",
        "chr": 4.0,
        "venue": null,
        "lect": [
            "DR. SITI ZUHAIDAH BINTI SHAHADAN"
        ],
        "dayTime": []
    },
    {
        "code": "NURF 4415",
        "sect": 45,
        "title": "FINAL YEAR RESEARCH PROJECT I",
        "chr": 4.0,
        "venue": null,
        "lect": [
            "DR. MOHD KHAIRUL ZUL HASYMI BIN FIRDAUS"
        ],
        "dayTime": []
    },
    {
        "code": "NURF 4415",
        "sect": 46,
        "title": "FINAL YEAR RESEARCH PROJECT I",
        "chr": 4.0,
        "venue": null,
        "lect": [
            "DR. AYUNI ASMA' BINTI BAHARUDIN"
        ],
        "dayTime": []
    },
    {
        "code": "NURF 4415",
        "sect": 47,
        "title": "FINAL YEAR RESEARCH PROJECT I",
        "chr": 4.0,
        "venue": null,
        "lect": [
            "DR. MUHAMMAD KAMIL BIN CHE HASAN"
        ],
        "dayTime": []
    }
]