[
    {
        "code": "PSYC 4995",
        "sect": 1,
        "title": "INDUSTRIAL TRAINING",
        "chr": 6.0,
        "venue": null,
        "lect": [
            "ASSOC. PROF. DR. MARIAM ADAWIAH BINTI DZULKIFLI"
        ],
        "dayTime": []
    },
    {
        "code": "PSYC 4995",
        "sect": 2,
        "title": "INDUSTRIAL TRAINING",
        "chr": 6.0,
        "venue": null,
        "lect": [
            "ASSOC. PROF. DR. LIHANNA BINTI BORHAN"
        ],
        "dayTime": []
    },
    {
        "code": "PSYC 4995",
        "sect": 3,
        "title": "INDUSTRIAL TRAINING",
        "chr": 6.0,
        "venue": null,
        "lect": [
            "ASSOC. PROF. DR. NAZARIAH SHAR'IE BINTI JANON"
        ],
        "dayTime": []
    },
    {
        "code": "PSYC 4995",
        "sect": 4,
        "title": "INDUSTRIAL TRAINING",
        "chr": 6.0,
        "venue": null,
        "lect": [
            "ASSOC. PROF. DR. NOR DIANA BINTI MOHD. MAHUDIN"
        ],
        "dayTime": []
    },
    {
        "code": "PSYC 4995",
        "sect": 5,
        "title": "INDUSTRIAL TRAINING",
        "chr": 6.0,
        "venue": null,
        "lect": [
            "ASSOC. PROF. DR. RUHAYA BINTI HUSSIN"
        ],
        "dayTime": []
    },
    {
        "code": "PSYC 4995",
        "sect": 6,
        "title": "INDUSTRIAL TRAINING",
        "chr": 6.0,
        "venue": null,
        "lect": [
            "ASSOC. PROF. DR. JAMILAH HANUM BINTI ABDUL KHAIYOM"
        ],
        "dayTime": []
    },
    {
        "code": "PSYC 4995",
        "sect": 7,
        "title": "INDUSTRIAL TRAINING",
        "chr": 6.0,
        "venue": null,
        "lect": [
            "DR. MARDIANA BINTI MOHAMAD"
        ],
        "dayTime": []
    },
    {
        "code": "PSYC 4995",
        "sect": 8,
        "title": "INDUSTRIAL TRAINING",
        "chr": 6.0,
        "venue": null,
        "lect": [
            "DR. JUSMAWATI BINTI FAUZAMAN"
        ],
        "dayTime": []
    },
    {
        "code": "PSYC 4995",
        "sect": 9,
        "title": "INDUSTRIAL TRAINING",
        "chr": 6.0,
        "venue": null,
        "lect": [
            "DR. INTAN AIDURA BINTI ALIAS"
        ],
        "dayTime": []
    },
    {
        "code": "PSYC 4995",
        "sect": 10,
        "title": "INDUSTRIAL TRAINING",
        "chr": 6.0,
        "venue": null,
        "lect": [
            "DR. PAMILIA LOURDUNATHAN"
        ],
        "dayTime": []
    },
    {
        "code": "PSYC 4995",
        "sect": 11,
        "title": "INDUSTRIAL TRAINING",
        "chr": 6.0,
        "venue": null,
        "lect": [
            "DR. NURUL MIZA BINTI MOHD RASHID"
        ],
        "dayTime": []
    },
    {
        "code": "PSYC 4995",
        "sect": 12,
        "title": "INDUSTRIAL TRAINING",
        "chr": 6.0,
        "venue": null,
        "lect": [
            "DR. SURIATI BINTI SIDEK"
        ],
        "dayTime": []
    },
    {
        "code": "PSYC 4995",
        "sect": 13,
        "title": "INDUSTRIAL TRAINING",
        "chr": 6.0,
        "venue": null,
        "lect": [
            "DR. MAISARAH BINTI MOHD. TAIB"
        ],
        "dayTime": []
    },
    {
        "code": "PSYC 4995",
        "sect": 14,
        "title": "INDUSTRIAL TRAINING",
        "chr": 6.0,
        "venue": null,
        "lect": [
            "DR. MOHD FERDAUS BIN HARUN"
        ],
        "dayTime": []
    },
    {
        "code": "PSYC 4995",
        "sect": 15,
        "title": "INDUSTRIAL TRAINING",
        "chr": 6.0,
        "venue": null,
        "lect": [
            "DR. USMAN JAFFER"
        ],
        "dayTime": []
    },
    {
        "code": "PSYC 4995",
        "sect": 16,
        "title": "INDUSTRIAL TRAINING",
        "chr": 6.0,
        "venue": null,
        "lect": [
            "DR. MOHD TAUFIK BIN MOHAMMAD"
        ],
        "dayTime": []
    },
    {
        "code": "PSYC 4995",
        "sect": 17,
        "title": "INDUSTRIAL TRAINING",
        "chr": 6.0,
        "venue": null,
        "lect": [
            "DR. SITI INARAH BINTI HASIM @ HASHIM"
        ],
        "dayTime": []
    },
    {
        "code": "PSYC 4995",
        "sect": 18,
        "title": "INDUSTRIAL TRAINING",
        "chr": 6.0,
        "venue": null,
        "lect": [
            "NURUL IZZATI ASYIKIN BINTI ZULKIFLY"
        ],
        "dayTime": []
    },
    {
        "code": "PSYC 4995",
        "sect": 19,
        "title": "INDUSTRIAL TRAINING",
        "chr": 6.0,
        "venue": null,
        "lect": [
            "NUR AINI ALEGREA SUNER"
        ],
        "dayTime": []
    },
    {
        "code": "PSYC 4995",
        "sect": 20,
        "title": "INDUSTRIAL TRAINING",
        "chr": 6.0,
        "venue": null,
        "lect": [
            "SYED AHMAD MUHAJIR ALHADDAD BIN SYED ESA"
        ],
        "dayTime": []
    },
    {
        "code": "PSYC 4995",
        "sect": 21,
        "title": "INDUSTRIAL TRAINING",
        "chr": 6.0,
        "venue": null,
        "lect": [
            "MUHAMAD KARIMI BIN SULAIMAN"
        ],
        "dayTime": []
    },
    {
        "code": "PSYC 4995",
        "sect": 22,
        "title": "INDUSTRIAL TRAINING",
        "chr": 6.0,
        "venue": null,
        "lect": [
            "MUHAMMAD HAIKAL B. AHMAD PUA'AD"
        ],
        "dayTime": []
    },
    {
        "code": "SOCA 4699",
        "sect": 1,
        "title": "INTERNSHIP",
        "chr": 6.0,
        "venue": null,
        "lect": [
            "DR. NOR AISAH BINTI AREFF"
        ],
        "dayTime": []
    },
    {
        "code": "SOCA 4699",
        "sect": 2,
        "title": "INTERNSHIP",
        "chr": 6.0,
        "venue": null,
        "lect": [
            "PROF. DR. HAZIZAN B. MD. NOON"
        ],
        "dayTime": []
    },
    {
        "code": "SOCA 4699",
        "sect": 3,
        "title": "INTERNSHIP",
        "chr": 6.0,
        "venue": null,
        "lect": [
            "ASSOC. PROF. DR. ROHAIZA BINTI ABD. ROKIS"
        ],
        "dayTime": []
    },
    {
        "code": "SOCA 4699",
        "sect": 4,
        "title": "INTERNSHIP",
        "chr": 6.0,
        "venue": null,
        "lect": [
            "ASSOC. PROF. DR. NURAZZURA BT MOHAMAD DIAH"
        ],
        "dayTime": []
    },
    {
        "code": "SOCA 4699",
        "sect": 5,
        "title": "INTERNSHIP",
        "chr": 6.0,
        "venue": null,
        "lect": [
            "ASSOC. PROF. DR. NOOR AZLAN B. MOHD NOOR"
        ],
        "dayTime": []
    },
    {
        "code": "SOCA 4699",
        "sect": 6,
        "title": "INTERNSHIP",
        "chr": 6.0,
        "venue": null,
        "lect": [
            "DR. NORASIKIN BT BASIR"
        ],
        "dayTime": []
    },
    {
        "code": "SOCA 4699",
        "sect": 7,
        "title": "INTERNSHIP",
        "chr": 6.0,
        "venue": null,
        "lect": [
            "DR. NOR AZLIN BINTI TAJUDDIN"
        ],
        "dayTime": []
    },
    {
        "code": "SOCA 4699",
        "sect": 8,
        "title": "INTERNSHIP",
        "chr": 6.0,
        "venue": null,
        "lect": [
            "DR. SZARIANNIE BINTI SULAIMAN"
        ],
        "dayTime": []
    },
    {
        "code": "SOCA 4699",
        "sect": 9,
        "title": "INTERNSHIP",
        "chr": 6.0,
        "venue": null,
        "lect": [
            "DR. SH FATIMAH ALZAHRAH BINTI SYED HUSSIEN"
        ],
        "dayTime": []
    },
    {
        "code": "SOCA 4699",
        "sect": 10,
        "title": "INTERNSHIP",
        "chr": 6.0,
        "venue": null,
        "lect": [
            "DR. IYAD M. Y. EID"
        ],
        "dayTime": []
    },
    {
        "code": "SOCA 4699",
        "sect": 11,
        "title": "INTERNSHIP",
        "chr": 6.0,
        "venue": null,
        "lect": [
            "DR. SOHELA MUSTARI"
        ],
        "dayTime": []
    }
]